asynctasklist/__init__.py
asynctasklist-0.3.dist-info/LICENSE
asynctasklist-0.3.dist-info/METADATA
asynctasklist-0.3.dist-info/WHEEL
asynctasklist-0.3.dist-info/top_level.txt
asynctasklist-0.3.dist-info/RECORD
