Metadata-Version: 2.1
Name: asynctasklist
Version: 0.3
Summary: a simple tasklist library for running tasks asynchronously or synchronously
Author: moojor224
License: Apache-2.0
Project-URL: Homepage, https://github.com/moojor224/asynctasklist
Project-URL: Changelog, https://github.com/moojor224/asynctasklist/releases
Project-URL: Issues, https://github.com/moojor224/asynctasklist/issues
Project-URL: CI, https://github.com/moojor224/asynctasklist/actions
Classifier: License :: OSI Approved :: Apache Software License
Requires-Python: >=2.7
License-File: LICENSE
Provides-Extra: test
Requires-Dist: pytest ; extra == 'test'
